dynamic_diffraction_module/Constants.py
dynamic_diffraction_module/__init__.py
dynamic_diffraction_module/bmirror.py
dynamic_diffraction_module/crystal.py
dynamic_diffraction_module/data_files/Hplanes_C.csv
dynamic_diffraction_module/data_files/__init__.py
dynamic_diffraction_module/data_files/alpha_si.dat
dynamic_diffraction_module/material_data.py
dynamic_diffraction_module/utils.py
dynamic_diffraction_module-0.1.0.dist-info/LICENSE
dynamic_diffraction_module-0.1.0.dist-info/METADATA
dynamic_diffraction_module-0.1.0.dist-info/WHEEL
dynamic_diffraction_module-0.1.0.dist-info/RECORD
