Metadata-Version: 2.1
Name: dynamic-diffraction-module
Version: 0.1.0
Summary: A python based framework for dynamic diffraction calculations of crystals.
Home-page: https://gitlab.desy.de/patrick.rauer/dynamic-diffraction-module
License: GPL-3.0-or-later
Author: Patrick Rauer
Author-email: patrick.rauer@desy.de
Requires-Python: >=3.7.1,<4.0
Classifier: Development Status :: 2 - Pre-Alpha
Classifier: Intended Audience :: Developers
Classifier: License :: OSI Approved :: GNU General Public License v3 or later (GPLv3+)
Classifier: License :: OSI Approved :: MIT License
Classifier: Natural Language :: English
Classifier: Programming Language :: Python :: 3
Classifier: Programming Language :: Python :: 3.8
Classifier: Programming Language :: Python :: 3.9
Classifier: Programming Language :: Python :: 3.10
Classifier: Programming Language :: Python :: 3.11
Classifier: Programming Language :: Python :: 3.7
Provides-Extra: dev
Provides-Extra: doc
Provides-Extra: test
Requires-Dist: black (>=21.5b2,<22.0) ; (python_full_version >= "3.6.2" and python_full_version < "4.0.0") and (extra == "test")
Requires-Dist: bump2version (>=1.0.1,<2.0.0) ; extra == "dev"
Requires-Dist: flake8 (>=3.9.2,<4.0.0) ; extra == "test"
Requires-Dist: flake8-docstrings (>=1.6.0,<2.0.0) ; extra == "test"
Requires-Dist: isort (>=5.8.0,<6.0.0) ; extra == "test"
Requires-Dist: matplotlib (>=3.5.1,<4.0.0) ; python_version < "3.8"
Requires-Dist: matplotlib (>=3.6.1,<4.0.0) ; python_version >= "3.8" and python_version < "4.0"
Requires-Dist: mkdocs (>=1.1.2,<2.0.0) ; extra == "doc"
Requires-Dist: mkdocs-autorefs (>=0.2.1,<0.3.0) ; extra == "doc"
Requires-Dist: mkdocs-include-markdown-plugin (>=1.0.0,<2.0.0) ; extra == "doc"
Requires-Dist: mkdocs-material (>=6.1.7,<7.0.0) ; extra == "doc"
Requires-Dist: mkdocs-material-extensions (>=1.0.1,<2.0.0) ; extra == "doc"
Requires-Dist: mkdocstrings (>=0.15.2,<0.16.0) ; extra == "doc"
Requires-Dist: mypy (>=0.900,<0.901) ; extra == "test"
Requires-Dist: numpy (>=1.20.1,<2.0.0) ; python_version < "3.8"
Requires-Dist: numpy (>=1.23.2,<2.0.0) ; python_version >= "3.8" and python_version < "4.0"
Requires-Dist: pandas (>=1.3,<2.0) ; python_version < "3.8"
Requires-Dist: pandas (>=2.0,<3.0) ; python_version >= "3.8" and python_version < "4.0"
Requires-Dist: pip (>=20.3.1,<21.0.0) ; extra == "dev"
Requires-Dist: pre-commit (>=2.12.0,<3.0.0) ; extra == "dev"
Requires-Dist: pytest (>=6.2.4,<7.0.0) ; extra == "test"
Requires-Dist: pytest-cov (>=2.12.0,<3.0.0) ; extra == "test"
Requires-Dist: toml (>=0.10.2,<0.11.0) ; extra == "dev"
Requires-Dist: tox (>=3.20.1,<4.0.0) ; extra == "dev"
Requires-Dist: twine (>=3.3.0,<4.0.0) ; extra == "dev"
Requires-Dist: virtualenv (>=20.2.2,<21.0.0) ; extra == "dev"
Requires-Dist: xraylib (>=4.0.1,<5.0.0)
